{
  "db_name": "PostgreSQL",
  "query": "SELECT name, status as \"status:ChallengeStatus\", category as \"category:ChallengeCategory\" FROM challenges WHERE id=$1",
  "describe": {
    "columns": [
      {
        "ordinal": 0,
        "name": "name",
        "type_info": "Varchar"
      },
      {
        "ordinal": 1,
        "name": "status:ChallengeStatus",
        "type_info": {
          "Custom": {
            "name": "challenge_status",
            "kind": {
              "Enum": [
                "draft",
                "beta",
                "public",
                "private"
              ]
            }
          }
        }
      },
      {
        "ordinal": 2,
        "name": "category:ChallengeCategory",
        "type_info": {
          "Custom": {
            "name": "challenge_category",
            "kind": {
              "Enum": [
                "code-golf",
                "restricted-source",
                "private",
                "code-challenge"
              ]
            }
          }
        }
      }
    ],
    "parameters": {
      "Left": [
        "Int4"
      ]
    },
    "nullable": [
      false,
      true,
      true
    ]
  },
  "hash": "cf53b917a82129b867bd238e0d22b1b9e83f34a3a3bf5f939787c44042362709"
}
