{
  "db_name": "PostgreSQL",
  "query": "UPDATE discord_messages\n                SET author=$1,\n                points=$2,\n                previous_author=$3,\n                previous_author_points=$4,\n                message_id=$5,\n                channel_id=$6\n                WHERE id=$7",
  "describe": {
    "columns": [],
    "parameters": {
      "Left": [
        "Int4",
        "Int4",
        "Int4",
        "Int4",
        "Int8",
        "Int8",
        "Int4"
      ]
    },
    "nullable": []
  },
  "hash": "3ba2fce1f89cd5647b6c919cce4ba7f661b1fb5943082879f1748ce28eb00562"
}
